{
  "version": 2,
  "extractor": "pdffigures2",
  "figures": [
    {
      "url": "assets/figures/arxiv/2604.01158v1/fig-001.webp",
      "caption": "Fig. 8: Hardware experiment snapshots. Representative real-world snapshots of our humanoid table-tennis system, showing diverse whole-body skills such as smash, low-crouching shots, lateral movements, and ego-centric onboard strikes.",
      "page": 11,
      "index": 1,
      "width": 1072,
      "height": 429
    },
    {
      "url": "assets/figures/arxiv/2604.01158v1/fig-002.webp",
      "caption": "Fig. 4: Egocentric onboard perception system. Our perception pipeline combines YOLO-based ball detection, AprilTag-based robot localization, and adaptive Kalman filtering for state estimation. The resulting system provides robust real-time ball trajectory prediction and strike-target estimation using only onboard sensing.",
      "page": 7,
      "index": 2,
      "width": 1072,
      "height": 377
    },
    {
      "url": "assets/figures/arxiv/2604.01158v1/fig-003.webp",
      "caption": "TABLE IV: Policy evaluations in simulation.",
      "page": 10,
      "index": 3,
      "width": 1076,
      "height": 400
    },
    {
      "url": "assets/figures/arxiv/2604.01158v1/fig-004.webp",
      "caption": "Fig. 5: Motion-VAE expands strike-space coverage. Compared with the original mocap dataset, Motion-VAE-generated motions produce a much broader distribution of strike targets over the reachable hitting workspace, substantially improving data coverage for downstream policy learning.",
      "page": 10,
      "index": 4,
      "width": 1129,
      "height": 267
    },
    {
      "url": "assets/figures/arxiv/2604.01158v1/fig-005.webp",
      "caption": "Fig. 7: Comparison between physically implausible strike motions (top) and motions corrected by Tracker Filter (bottom).",
      "page": 10,
      "index": 5,
      "width": 508,
      "height": 352
    },
    {
      "url": "assets/figures/arxiv/2604.01158v1/fig-006.webp",
      "caption": "Fig. 11: Strike-point distribution and return performance. Forehand and backhand strike points are visualized together with the corresponding hit-and-return statistics across the reachable hitting workspace.",
      "page": 14,
      "index": 6,
      "width": 1072,
      "height": 458
    },
    {
      "url": "assets/figures/arxiv/2604.01158v1/fig-007.webp",
      "caption": "TABLE VI: Perception module ablation study.",
      "page": 13,
      "index": 7,
      "width": 962,
      "height": 225
    },
    {
      "url": "assets/figures/arxiv/2604.01158v1/fig-008.webp",
      "caption": "Fig. 3: Motion-VAE for scalable strike motion generation.",
      "page": 4,
      "index": 8,
      "width": 508,
      "height": 317
    },
    {
      "url": "assets/figures/arxiv/2604.01158v1/fig-009.webp",
      "caption": "Fig. 9: Perception snapshots. Real-time examples of onboard ball detection, HSV segmentation, ball-state estimation, and trajectory prediction during play.",
      "page": 12,
      "index": 9,
      "width": 1072,
      "height": 306
    },
    {
      "url": "assets/figures/arxiv/2604.01158v1/fig-010.webp",
      "caption": "Fig. 10: Egocentric Perception Noise. The plots show the error distribution of position (left), velocity (center), and temporal estimation (right) as a function of remaining time to strike. The horizontal axis represents the ground-truth time-to-strike, while the vertical axis denotes the magnitude of the respective estimation errors. The solid lines represent the mean error, and the shaded areas indicate the standard deviation.",
      "page": 12,
      "index": 10,
      "width": 1072,
      "height": 248
    },
    {
      "url": "assets/figures/arxiv/2604.01158v1/fig-011.webp",
      "caption": "TABLE III: Evaluation metrics.",
      "page": 9,
      "index": 11,
      "width": 516,
      "height": 342
    },
    {
      "url": "assets/figures/arxiv/2604.01158v1/fig-012.webp",
      "caption": "TABLE I: Asymmetric observation design for actor and critic.",
      "page": 5,
      "index": 12,
      "width": 506,
      "height": 488
    }
  ]
}