{
  "version": 2,
  "extractor": "pdffigures2",
  "figures": [
    {
      "url": "assets/figures/arxiv/2603.27993v1/fig-001.webp",
      "caption": "Figure 7: Failure cases of PPCR.",
      "page": 11,
      "index": 1,
      "width": 462,
      "height": 357
    },
    {
      "url": "assets/figures/arxiv/2603.27993v1/fig-002.webp",
      "caption": "Table 1: Comparison of referring image segmentation methods on RefCOCO, RefCOCO+, and RefCOCOg. †means the results are excerpted from the original paper.",
      "page": 7,
      "index": 2,
      "width": 971,
      "height": 349
    },
    {
      "url": "assets/figures/arxiv/2603.27993v1/fig-003.webp",
      "caption": "Figure 6: Qualitative comparisons on RefCOCOg. From left to right: Ground-Truth masks (GT), GLaMM results, PPCR results, the Spatial Segmentation Prompt Ground Truth (Spatial SP GT), and the Spatial Segmentation Prompt (Spatial SP).",
      "page": 10,
      "index": 3,
      "width": 783,
      "height": 717
    },
    {
      "url": "assets/figures/arxiv/2603.27993v1/fig-004.webp",
      "caption": "Figure 3: Overview of PPCR for referring image segmentation. The framework follows a Semantic UnderstandingSpatial Grounding-Instance Segmentation pipeline. Given an image and a referring expression, a multimodal large language model first generates a Semantic Segmentation Prompt (Semantic SP) via the LoRA A branch, which then guides the generation of a Spatial Segmentation Prompt (Spatial SP) via the LoRA B branch. The Spatial Segmentation Prompt is mapped to bounding box coordinates, and is jointly used with the Semantic Segmentation Prompt by SAM for instance segmentation. Purple and orange arrows denote semantic and spatial information flows.",
      "page": 3,
      "index": 4,
      "width": 736,
      "height": 369
    },
    {
      "url": "assets/figures/arxiv/2603.27993v1/fig-005.webp",
      "caption": "Table 2: Ablation study on different reasoning mechanisms on RefCOCO, RefCOCO+, and RefCOCOg.",
      "page": 8,
      "index": 5,
      "width": 971,
      "height": 187
    },
    {
      "url": "assets/figures/arxiv/2603.27993v1/fig-006.webp",
      "caption": "Figure 4: Illustration of the Semantic Prompt Template used in the Semantic Understanding stage.",
      "page": 4,
      "index": 6,
      "width": 456,
      "height": 266
    }
  ]
}